mosum/__init__.py
mosum/bandwidth.py
mosum/bootstrap.py
mosum/bottom_up.py
mosum/classes.py
mosum/exhaust_bic.py
mosum/local_prune.py
mosum/mosum.py
mosum/mosum_stat.py
mosum/mosum_test.py
mosum/mosum_util.cpp
mosum/mosum_util.h
mosum/persp3D.py
mosum/test_data.py
mosum/test_models.py
mosum-0.2.0.dist-info/LICENSE
mosum-0.2.0.dist-info/WHEEL
mosum-0.2.0.dist-info/METADATA
mosum-0.2.0.dist-info/RECORD
