Metadata-Version: 2.1
Name: mosum
Version: 0.2.0
Summary: Moving Sum Based Procedures for Changes in the Mean
License: MIT
Author: Dom Owens
Author-email: dom.owens@bristol.ac.uk
Requires-Python: >=3.9,<3.10
Classifier: License :: OSI Approved :: MIT License
Classifier: Programming Language :: Python :: 3
Classifier: Programming Language :: Python :: 3.9
Requires-Dist: matplotlib (>=3.6.3,<4.0.0)
Requires-Dist: numba (>=0.53,<0.54)
Requires-Dist: numpy (>=1.23.5,<1.24)
Requires-Dist: pandas (>=1.5.3,<2.0.0)
